banditbench/__init__.py
banditbench/bench.py
banditbench/utils.py
banditbench/version.py
banditbench/agents/__init__.py
banditbench/agents/classics.py
banditbench/agents/context.py
banditbench/agents/guides.py
banditbench/agents/llm.py
banditbench/agents/types.py
banditbench/sampling/__init__.py
banditbench/sampling/sampler.py
banditbench/sampling/types.py
banditbench/tasks/__init__.py
banditbench/tasks/env.py
banditbench/tasks/scenario.py
banditbench/tasks/types.py
banditbench/tasks/cb/__init__.py
banditbench/tasks/cb/env.py
banditbench/tasks/cb/movielens/__init__.py
banditbench/tasks/cb/movielens/env.py
banditbench/tasks/cb/movielens/processing.py
banditbench/tasks/cb/movielens/scenario.py
banditbench/tasks/cb/movielens/data/geo-data.csv
banditbench/tasks/mab/__init__.py
banditbench/tasks/mab/env.py
banditbench/tasks/mab/scenarios.py
banditbench/training/__init__.py
banditbench/training/fewshot.py
banditbench/training/oracle_sft.py
banditbench-0.0.8.dist-info/LICENSE
banditbench-0.0.8.dist-info/METADATA
banditbench-0.0.8.dist-info/WHEEL
banditbench-0.0.8.dist-info/top_level.txt
banditbench-0.0.8.dist-info/RECORD
