Metadata-Version: 2.1
Name: banditbench
Version: 0.0.8
Summary: BanditBench: A Bandit Benchmark to Evaluate Self-Improving LLM Algorithms
Home-page: https://github.com/allenanie/EVOLvE
Author: Allen Nie
Author-email: anie@cs.stanford.edu
License: MIT LICENSE
Project-URL: Homepage, https://github.com/allenanie/EVOLvE
Project-URL: Documentation, https://github.com/allenanie/EVOLvE
Project-URL: Repository, https://github.com/allenanie/EVOLvE
Keywords: banditbench,Bandit,LLM,RL,Agent
Classifier: Development Status :: 4 - Beta
Classifier: Intended Audience :: Science/Research
Classifier: License :: OSI Approved :: MIT License
Classifier: Programming Language :: Python :: 3.9
Requires-Python: >=3.9
License-File: LICENSE
Requires-Dist: pydantic==2.10.5
Requires-Dist: litellm
Requires-Dist: pandas
Requires-Dist: tensorflow-datasets==4.9.3
Requires-Dist: tensorflow==2.17.0
Requires-Dist: ml-dtypes==0.3.1
Requires-Dist: matplotlib
Requires-Dist: scipy
